pytest_raisesregexp/__init__.py
pytest_raisesregexp/plugin.py
pytest_raisesregexp-2.1.dist-info/DESCRIPTION.rst
pytest_raisesregexp-2.1.dist-info/METADATA
pytest_raisesregexp-2.1.dist-info/RECORD
pytest_raisesregexp-2.1.dist-info/WHEEL
pytest_raisesregexp-2.1.dist-info/entry_points.txt
pytest_raisesregexp-2.1.dist-info/metadata.json
pytest_raisesregexp-2.1.dist-info/top_level.txt
