Metadata-Version: 2.0
Name: pytest-raisesregexp
Version: 2.1
Summary: Simple pytest plugin to look for regex in Exceptions
Home-page: https://github.com/Walkman/pytest_raisesregexp
Author: Kiss György
Author-email: kissgyorgy@me.com
License: UNKNOWN
Platform: UNKNOWN
Classifier: License :: OSI Approved :: MIT License
Classifier: Programming Language :: Python :: 2
Classifier: Programming Language :: Python :: 2.6
Classifier: Programming Language :: Python :: 2.7
Classifier: Programming Language :: Python :: 3
Classifier: Programming Language :: Python :: 3.3
Classifier: Programming Language :: Python :: 3.4
Classifier: Programming Language :: Python :: Implementation :: PyPy
Classifier: Topic :: Software Development :: Testing
Requires-Dist: py
Requires-Dist: pytest
